LICENSE.md
flux/__init__.py
flux/__main__.py
flux/backend/__init__.py
flux/backend/applied_migration.py
flux/backend/base.py
flux/backend/get_backends.py
flux/builtins/postgres.py
flux/cli.py
flux/config.py
flux/constants.py
flux/exceptions.py
flux/migration/__init__.py
flux/migration/migration.py
flux/migration/read_migration.py
flux/migration/temporary_module.py
flux/runner.py
flux_migrations-0.0.3.dist-info/LICENSE.md
flux_migrations-0.0.3.dist-info/METADATA
flux_migrations-0.0.3.dist-info/WHEEL
flux_migrations-0.0.3.dist-info/entry_points.txt
flux_migrations-0.0.3.dist-info/RECORD
