Metadata-Version: 2.1
Name: flux-migrations
Version: 0.0.3
Summary: A database migration tool that works well with Python projects
Home-page: https://github.com/k2bd/flux-migrations
License: MIT
Author: Kevin Duff
Author-email: kevinkelduff@gmail.com
Requires-Python: >=3.10,<4.0
Classifier: Development Status :: 1 - Planning
Classifier: Intended Audience :: Developers
Classifier: License :: OSI Approved :: MIT License
Classifier: Operating System :: OS Independent
Classifier: Programming Language :: Python
Classifier: Programming Language :: Python :: 3
Classifier: Programming Language :: Python :: 3.10
Classifier: Programming Language :: Python :: 3.11
Classifier: Programming Language :: Python :: 3.12
Classifier: Programming Language :: Python :: 3.13
Classifier: Programming Language :: Python :: 3 :: Only
Classifier: Topic :: Database
Classifier: Topic :: Software Development :: Libraries
Provides-Extra: postgres
Requires-Dist: aiopg (>=1.4.0,<2.0.0) ; extra == "postgres"
Requires-Dist: asyncpg (>=0.29.0,<0.30.0) ; extra == "postgres"
Requires-Dist: databases (>=0.9.0,<0.10.0) ; extra == "postgres"
Requires-Dist: sqlparse (>=0.5.1,<0.6.0) ; extra == "postgres"
Requires-Dist: toml (>=0.10.2,<0.11.0)
Requires-Dist: typer (>=0.12.3,<0.13.0)
Project-URL: Repository, https://github.com/k2bd/flux-migrations
